LICENSE
MANIFEST.in
README.md
setup.py
django_misery/__init__.py
django_misery/admin.py
django_misery/middleware.py
django_misery/models.py
django_misery.egg-info/PKG-INFO
django_misery.egg-info/SOURCES.txt
django_misery.egg-info/dependency_links.txt
django_misery.egg-info/top_level.txt
django_misery/templates/django_misery/ASPerror.html