Metadata-Version: 1.0
Name: django-misery
Version: 0.0.3
Summary: A simple ban system for Django, that does nasty stuff to trolls wandering on your website.
Home-page: https://bitbucket.org/fschwebel/django-misery/
Author: Fabien Schwebel
Author-email: fabien@schwebel.com
License: MIT License
Keywords: django misery hellban slowban
Platform: UNKNOWN
Classifier: Development Status :: 3 - Alpha
Classifier: Environment :: Web Environment
Classifier: Framework :: Django
Classifier: Topic :: Utilities
Classifier: Intended Audience :: Developers
Classifier: License :: OSI Approved :: MIT License
Classifier: Operating System :: OS Independent
Classifier: Programming Language :: Python
Classifier: Topic :: Software Development :: Libraries :: Python Modules
